hashget/heuristics/kernel_org/__init__.py
hashget_kernel_org-0.9.dist-info/METADATA
hashget_kernel_org-0.9.dist-info/WHEEL
hashget_kernel_org-0.9.dist-info/top_level.txt
hashget_kernel_org-0.9.dist-info/RECORD
