Metadata-Version: 2.1
Name: hashget-kernel-org
Version: 0.9
Summary: kernel.org (linux kernel sources) plugin for hashget
Home-page: https://github.com/yaroslaff/hashget
Author: Yaroslav Polyakov
Author-email: yaroslaff@gmail.com
License: Apache Software License
Platform: UNKNOWN
